skll/__init__.py
skll/metrics.py
skll/types.py
skll/version.py
skll/config/__init__.py
skll/config/utils.py
skll/data/__init__.py
skll/data/dict_vectorizer.py
skll/data/featureset.py
skll/data/readers.py
skll/data/writers.py
skll/experiments/__init__.py
skll/experiments/input.py
skll/experiments/output.py
skll/experiments/utils.py
skll/learner/__init__.py
skll/learner/utils.py
skll/learner/voting.py
skll/utils/__init__.py
skll/utils/constants.py
skll/utils/logging.py
skll/utils/testing.py
skll/utils/wandb.py
skll/utils/commandline/__init__.py
skll/utils/commandline/compute_eval_from_predictions.py
skll/utils/commandline/filter_features.py
skll/utils/commandline/generate_predictions.py
skll/utils/commandline/join_features.py
skll/utils/commandline/plot_learning_curves.py
skll/utils/commandline/print_model_weights.py
skll/utils/commandline/run_experiment.py
skll/utils/commandline/skll_convert.py
skll/utils/commandline/summarize_results.py
skll-5.1.0.dist-info/LICENSE.txt
skll-5.1.0.dist-info/METADATA
skll-5.1.0.dist-info/WHEEL
skll-5.1.0.dist-info/entry_points.txt
skll-5.1.0.dist-info/top_level.txt
skll-5.1.0.dist-info/RECORD
