Metadata-Version: 2.1
Name: skll
Version: 5.1.0
Summary: SciKit-Learn Laboratory makes it easier to run machine learning experiments with scikit-learn.
Author-email: Nitin Madnani  <nmadnani@gmail.com>
Maintainer-email: Nitin Madnani  <nmadnani@gmail.com>, Tamar Lavee <tamarlv@hotmail.com>
License: New BSD License
Project-URL: Documentation, https://skll.readthedocs.org
Project-URL: Repository, http://github.com/EducationalTestingService/skll
Keywords: learning scikit-learn
Classifier: Intended Audience :: Science/Research
Classifier: Intended Audience :: Developers
Classifier: License :: OSI Approved :: BSD License
Classifier: Programming Language :: Python
Classifier: Topic :: Software Development
Classifier: Topic :: Scientific/Engineering
Classifier: Operating System :: Microsoft :: Windows
Classifier: Operating System :: POSIX
Classifier: Operating System :: Unix
Classifier: Operating System :: MacOS
Classifier: Programming Language :: Python :: 3
Classifier: Programming Language :: Python :: 3.10
Classifier: Programming Language :: Python :: 3.11
Classifier: Programming Language :: Python :: 3.12
Requires-Python: >=3.10
License-File: LICENSE.txt
Requires-Dist: beautifulsoup4
Requires-Dist: joblib
Requires-Dist: numpy
Requires-Dist: pandas
Requires-Dist: ruamel.yaml
Requires-Dist: scikit-learn <1.6.0,>=1.5.0
Requires-Dist: scipy
Requires-Dist: seaborn
Requires-Dist: tabulate
Requires-Dist: typing-extensions
Requires-Dist: wandb
